nolano/__init__.py
nolano/nolano.py
nolano/utils.py
nolano-0.0.1.dist-info/METADATA
nolano-0.0.1.dist-info/WHEEL
nolano-0.0.1.dist-info/top_level.txt
nolano-0.0.1.dist-info/RECORD
