Metadata-Version: 2.4
Name: nolano
Version: 0.0.1
Summary: A Python package for interacting with Nolano's time series forecasting API
Author-email: Nolano Team <hello@nolano.ai>
License-Expression: MIT
Project-URL: Documentation, https://docs.nolano.ai
Project-URL: Source, https://github.com/nolano/nolano-python
Project-URL: API, https://app.nolano.ai
Classifier: Programming Language :: Python :: 3
Classifier: Operating System :: OS Independent
Requires-Python: >=3.8
Requires-Dist: requests
Requires-Dist: pandas
Requires-Dist: numpy<2.0
Requires-Dist: matplotlib
Provides-Extra: dev
Requires-Dist: black>=21.0; extra == "dev"
Requires-Dist: flake8>=3.8; extra == "dev"
Requires-Dist: mypy>=0.800; extra == "dev"
